karton_autoit_ripper-1.2.0-nspkg.pth
karton/autoit_ripper/__init__.py
karton/autoit_ripper/__main__.py
karton/autoit_ripper/__version__.py
karton/autoit_ripper/autoit.yar
karton/autoit_ripper/autoit_ripper_karton.py
karton/autoit_ripper/extract_drop.py
karton_autoit_ripper-1.2.0.dist-info/LICENSE
karton_autoit_ripper-1.2.0.dist-info/METADATA
karton_autoit_ripper-1.2.0.dist-info/WHEEL
karton_autoit_ripper-1.2.0.dist-info/entry_points.txt
karton_autoit_ripper-1.2.0.dist-info/namespace_packages.txt
karton_autoit_ripper-1.2.0.dist-info/top_level.txt
karton_autoit_ripper-1.2.0.dist-info/RECORD
