Metadata-Version: 2.1
Name: karton-autoit-ripper
Version: 1.2.0
Summary: AutoIt script ripper for Karton framework
Home-page: https://github.com/CERT-Polska/karton-autoit-ripper/
License: UNKNOWN
Platform: UNKNOWN
Classifier: Programming Language :: Python
Classifier: Operating System :: OS Independent
Requires-Dist: autoit-ripper (==1.1.0)
Requires-Dist: karton-core (<6.0.0,>=5.0.0)
Requires-Dist: malduck (==4.1.0)
Requires-Dist: regex (==2020.2.20)
